Modules/__init__.py
Modules/Network/Layer.py
Modules/Network/Network.py
Modules/Network/Neuron.py
Modules/Network/__init__.py
Modules/UI/__init__.py
Modules/UI/Shared/MenuBar.py
Modules/UI/Shared/__init__.py
MM_Simple_NeuralNetwork-0.1.1.dist-info/METADATA
MM_Simple_NeuralNetwork-0.1.1.dist-info/WHEEL
MM_Simple_NeuralNetwork-0.1.1.dist-info/top_level.txt
MM_Simple_NeuralNetwork-0.1.1.dist-info/RECORD
