Metadata-Version: 2.1
Name: MM-Simple-NeuralNetwork
Version: 0.1.1
Summary: A sample Neural Network project
Home-page: https://github.com/MathewLiam/NeuralNetwork
Author: Mathew McPherson
Author-email: Mathew.Liam.McPherosn@gmail.com
License: UNKNOWN
Project-URL: Bug Reports, https://github.com/MathewLiam/NeuralNetwork/issues
Project-URL: Source, https://github.com/MathewLiam/NeuralNetwork/issues
Keywords: AI,Neural Networks,Machine Learing
Platform: UNKNOWN
Requires-Python: >=3.6, <4
Provides-Extra: dev
Requires-Dist: check-manifest ; extra == 'dev'
Provides-Extra: test
Requires-Dist: unittest ; extra == 'test'
Requires-Dist: coverage ; extra == 'test'
